{
  "entries": [
    {
      "name": "TEXT_INFO_BEGIN_0",
      "variables": [
        {
          "type": "Int",
          "value": "1"
        }
      ],
      "children": [
        {
          "name": "TEXT_INFO_0",
          "variables": [
            {
              "type": "Int",
              "value": "1802645217"
            },
            {
              "type": "Int",
              "value": "0"
            },
            {
              "type": "String",
              "value": "球进了————！惊人的炸裂射门！\\n一切都发生在一瞬之间！"
            },
            {
              "type": "Int",
              "value": "0"
            }
          ],
          "children": []
        }
      ]
    }
  ]
}