{
  "entries": [
    {
      "name": "TEXT_INFO_BEGIN_0",
      "variables": [
        {
          "type": "Int",
          "value": "5"
        }
      ],
      "children": [
        {
          "name": "TEXT_INFO_0",
          "variables": [
            {
              "type": "Int",
              "value": "1121490439"
            },
            {
              "type": "Int",
              "value": "0"
            },
            {
              "type": "String",
              "value": "We've made it all the way to the nationals..."
            },
            {
              "type": "Int",
              "value": "0"
            }
          ],
          "children": []
        },
        {
          "name": "TEXT_INFO_1",
          "variables": [
            {
              "type": "Int",
              "value": "1777714628"
            },
            {
              "type": "Int",
              "value": "0"
            },
            {
              "type": "String",
              "value": "Well, well, if it isn't the crew from <MNT:NAGUMOHARA>.\\nFresh from the sticks."
            },
            {
              "type": "Int",
              "value": "0"
            }
          ],
          "children": []
        },
        {
          "name": "TEXT_INFO_2",
          "variables": [
            {
              "type": "Int",
              "value": "1894708357"
            },
            {
              "type": "Int",
              "value": "0"
            },
            {
              "type": "String",
              "value": "I know better than anyone how much of a nobody I am.\\n<MNT:NAGUMOHARA> has plenty of players who could replace me..."
            },
            {
              "type": "Int",
              "value": "0"
            }
          ],
          "children": []
        },
        {
          "name": "TEXT_INFO_3",
          "variables": [
            {
              "type": "Int",
              "value": "1068458562"
            },
            {
              "type": "Int",
              "value": "0"
            },
            {
              "type": "String",
              "value": "<FUL:SOJI>... What an eyesore."
            },
            {
              "type": "Int",
              "value": "0"
            }
          ],
          "children": []
        },
        {
          "name": "TEXT_INFO_4",
          "variables": [
            {
              "type": "Int",
              "value": "344076673"
            },
            {
              "type": "Int",
              "value": "0"
            },
            {
              "type": "String",
              "value": "Why...? Why can't I do it?!"
            },
            {
              "type": "Int",
              "value": "0"
            }
          ],
          "children": []
        }
      ]
    }
  ]
}