{
  "entries": [
    {
      "name": "TEXT_INFO_BEGIN_0",
      "variables": [
        {
          "type": "Int",
          "value": "8"
        }
      ],
      "children": [
        {
          "name": "TEXT_INFO_0",
          "variables": [
            {
              "type": "Int",
              "value": "-1444670125"
            },
            {
              "type": "Int",
              "value": "0"
            },
            {
              "type": "String",
              "value": "<FLC:KAZEMARU>! That was just fantastic!"
            },
            {
              "type": "Int",
              "value": "0"
            }
          ],
          "children": []
        },
        {
          "name": "TEXT_INFO_1",
          "variables": [
            {
              "type": "Int",
              "value": "-2100738416"
            },
            {
              "type": "Int",
              "value": "0"
            },
            {
              "type": "String",
              "value": "The Wind God's Dance, huh?\\nNow we've got nothing to worry about!"
            },
            {
              "type": "Int",
              "value": "0"
            }
          ],
          "children": []
        },
        {
          "name": "TEXT_INFO_2",
          "variables": [
            {
              "type": "Int",
              "value": "-1680705583"
            },
            {
              "type": "Int",
              "value": "0"
            },
            {
              "type": "String",
              "value": "Everyone keeps getting stronger...\\nI need to step up too, or I'll...!"
            },
            {
              "type": "Int",
              "value": "0"
            }
          ],
          "children": []
        },
        {
          "name": "TEXT_INFO_3",
          "variables": [
            {
              "type": "Int",
              "value": "-728506090"
            },
            {
              "type": "Int",
              "value": "0"
            },
            {
              "type": "String",
              "value": "<FLC:MIDORIKAWA>... hasn't your football changed\\nsince we all started playing for fun again?"
            },
            {
              "type": "Int",
              "value": "0"
            }
          ],
          "children": []
        },
        {
          "name": "TEXT_INFO_4",
          "variables": [
            {
              "type": "Int",
              "value": "-846671785"
            },
            {
              "type": "Int",
              "value": "0"
            },
            {
              "type": "String",
              "value": "After Alius Academy fell, you truly enjoyed the game.\\nYou chased the ball with everything you had\\nand got back up every time you fell."
            },
            {
              "type": "Int",
              "value": "0"
            }
          ],
          "children": []
        },
        {
          "name": "TEXT_INFO_5",
          "variables": [
            {
              "type": "Int",
              "value": "-425360492"
            },
            {
              "type": "Int",
              "value": "0"
            },
            {
              "type": "String",
              "value": "That's why you could go toe-to-toe even with\\nformer Epsilon and Genesis players."
            },
            {
              "type": "Int",
              "value": "0"
            }
          ],
          "children": []
        },
        {
          "name": "TEXT_INFO_6",
          "variables": [
            {
              "type": "Int",
              "value": "-4279595"
            },
            {
              "type": "Int",
              "value": "0"
            },
            {
              "type": "String",
              "value": "You'll be okay.\\nJust believe in yourself, and believe in the game."
            },
            {
              "type": "Int",
              "value": "0"
            }
          ],
          "children": []
        },
        {
          "name": "TEXT_INFO_7",
          "variables": [
            {
              "type": "Int",
              "value": "2015800858"
            },
            {
              "type": "Int",
              "value": "0"
            },
            {
              "type": "String",
              "value": "Believe in myself..."
            },
            {
              "type": "Int",
              "value": "0"
            }
          ],
          "children": []
        }
      ]
    }
  ]
}