{
  "entries": [
    {
      "name": "TEXT_INFO_BEGIN_0",
      "variables": [
        {
          "type": "Int",
          "value": "6"
        }
      ],
      "children": [
        {
          "name": "TEXT_INFO_0",
          "variables": [
            {
              "type": "Int",
              "value": "496501520"
            },
            {
              "type": "Int",
              "value": "0"
            },
            {
              "type": "String",
              "value": "... Puh."
            },
            {
              "type": "Int",
              "value": "0"
            }
          ],
          "children": []
        },
        {
          "name": "TEXT_INFO_1",
          "variables": [
            {
              "type": "Int",
              "value": "917852371"
            },
            {
              "type": "Int",
              "value": "0"
            },
            {
              "type": "String",
              "value": "<FST:UNMEI>, was ist los mit dir?\\nWogegen hast du denn gerade getreten?"
            },
            {
              "type": "Int",
              "value": "0"
            }
          ],
          "children": []
        },
        {
          "name": "TEXT_INFO_2",
          "variables": [
            {
              "type": "Int",
              "value": "799957394"
            },
            {
              "type": "Int",
              "value": "0"
            },
            {
              "type": "String",
              "value": "Das macht er hin und wieder ...\\nIch hab mich daran schon gewöhnt."
            },
            {
              "type": "Int",
              "value": "0"
            }
          ],
          "children": []
        },
        {
          "name": "TEXT_INFO_3",
          "variables": [
            {
              "type": "Int",
              "value": "1626339157"
            },
            {
              "type": "Int",
              "value": "0"
            },
            {
              "type": "String",
              "value": "Alles in Ordnung?"
            },
            {
              "type": "Int",
              "value": "0"
            }
          ],
          "children": []
        },
        {
          "name": "TEXT_INFO_4",
          "variables": [
            {
              "type": "Int",
              "value": "2046084628"
            },
            {
              "type": "Int",
              "value": "0"
            },
            {
              "type": "String",
              "value": "Äh ... ja, es ist nichts."
            },
            {
              "type": "Int",
              "value": "0"
            }
          ],
          "children": []
        },
        {
          "name": "TEXT_INFO_5",
          "variables": [
            {
              "type": "Int",
              "value": "1389991383"
            },
            {
              "type": "Int",
              "value": "0"
            },
            {
              "type": "String",
              "value": "Bälle, die nur ich sehen kann. Das muss eine Art Halluzination sein,\\ndie aus meiner starken Leidenschaft für Fußball entstanden ist ...\\nAber ... jetzt sogar Spieler ...?"
            },
            {
              "type": "Int",
              "value": "0"
            }
          ],
          "children": []
        }
      ]
    }
  ]
}