{
  "entries": [
    {
      "name": "TEXT_INFO_BEGIN_0",
      "variables": [
        {
          "type": "Int",
          "value": "4"
        }
      ],
      "children": [
        {
          "name": "TEXT_INFO_0",
          "variables": [
            {
              "type": "Int",
              "value": "-1253666962"
            },
            {
              "type": "Int",
              "value": "0"
            },
            {
              "type": "String",
              "value": "...?!"
            },
            {
              "type": "Int",
              "value": "0"
            }
          ],
          "children": []
        },
        {
          "name": "TEXT_INFO_1",
          "variables": [
            {
              "type": "Int",
              "value": "-1637098323"
            },
            {
              "type": "Int",
              "value": "0"
            },
            {
              "type": "String",
              "value": "Was war das für eine Technik?"
            },
            {
              "type": "Int",
              "value": "0"
            }
          ],
          "children": []
        },
        {
          "name": "TEXT_INFO_2",
          "variables": [
            {
              "type": "Int",
              "value": "-2022642196"
            },
            {
              "type": "Int",
              "value": "0"
            },
            {
              "type": "String",
              "value": "Es ist riskant, wenn wir ihre Taktiken nicht kennen.\\nWir müssen erst mal den Ball hin- und her spielen,\\num ihren Spielstil herauszufinden."
            },
            {
              "type": "Int",
              "value": "0"
            }
          ],
          "children": []
        },
        {
          "name": "TEXT_INFO_3",
          "variables": [
            {
              "type": "Int",
              "value": "-936281301"
            },
            {
              "type": "Int",
              "value": "0"
            },
            {
              "type": "String",
              "value": "Ich muss einen Weg finden, diese Verrückten zu besiegen.\\nUm <FST:OTONASHI> zu retten."
            },
            {
              "type": "Int",
              "value": "0"
            }
          ],
          "children": []
        }
      ]
    }
  ]
}