{
  "entries": [
    {
      "name": "TEXT_INFO_BEGIN_0",
      "variables": [
        {
          "type": "Int",
          "value": "11"
        }
      ],
      "children": [
        {
          "name": "TEXT_INFO_0",
          "variables": [
            {
              "type": "Int",
              "value": "-1301986291"
            },
            {
              "type": "Int",
              "value": "0"
            },
            {
              "type": "String",
              "value": "Nur noch ein bisschen!\\nHalte durch, Affenmonkey! Los, Kopra-Kobra!\\nMach den Tentakraken platt!"
            },
            {
              "type": "Int",
              "value": "0"
            }
          ],
          "children": []
        },
        {
          "name": "TEXT_INFO_1",
          "variables": [
            {
              "type": "Int",
              "value": "-1723328562"
            },
            {
              "type": "Int",
              "value": "0"
            },
            {
              "type": "String",
              "value": "Oh mein Gott!\\nIch hab tatsächlich ein Boss-Meckemon besiegt!"
            },
            {
              "type": "Int",
              "value": "0"
            }
          ],
          "children": []
        },
        {
          "name": "TEXT_INFO_2",
          "variables": [
            {
              "type": "Int",
              "value": "-2142034289"
            },
            {
              "type": "Int",
              "value": "0"
            },
            {
              "type": "String",
              "value": "Gut gemacht, Ma'am."
            },
            {
              "type": "Int",
              "value": "0"
            }
          ],
          "children": []
        },
        {
          "name": "TEXT_INFO_3",
          "variables": [
            {
              "type": "Int",
              "value": "-820858808"
            },
            {
              "type": "Int",
              "value": "0"
            },
            {
              "type": "String",
              "value": "Jetzt kann ich endlich meiner Enkelin\\nbei ihren Bosskämpfen helfen."
            },
            {
              "type": "Int",
              "value": "0"
            }
          ],
          "children": []
        },
        {
          "name": "TEXT_INFO_4",
          "variables": [
            {
              "type": "Int",
              "value": "-704020215"
            },
            {
              "type": "Int",
              "value": "0"
            },
            {
              "type": "String",
              "value": "Oma! Da bist du ja!\\nDu warst in letzter Zeit kaum zu Hause –\\nich hab mir schon Sorgen gemacht!"
            },
            {
              "type": "Int",
              "value": "0"
            }
          ],
          "children": []
        },
        {
          "name": "TEXT_INFO_5",
          "variables": [
            {
              "type": "Int",
              "value": "-47918390"
            },
            {
              "type": "Int",
              "value": "0"
            },
            {
              "type": "String",
              "value": "Oh je, tut mir leid!"
            },
            {
              "type": "Int",
              "value": "0"
            }
          ],
          "children": []
        },
        {
          "name": "TEXT_INFO_6",
          "variables": [
            {
              "type": "Int",
              "value": "-465575029"
            },
            {
              "type": "Int",
              "value": "0"
            },
            {
              "type": "String",
              "value": "Ich wollte den Tentakraken doch mit dir besiegen,\\n<FUL:MI-CHAN>. Deshalb musste ich auch trainieren ..."
            },
            {
              "type": "Int",
              "value": "0"
            }
          ],
          "children": []
        },
        {
          "name": "TEXT_INFO_7",
          "variables": [
            {
              "type": "Int",
              "value": "1671954244"
            },
            {
              "type": "Int",
              "value": "0"
            },
            {
              "type": "String",
              "value": "Oh, den Tentakraken haben wir schon besiegt!\\nJetzt kämpfen wir gegen die Mutter Gorgone.\\nDie ist richtig gruselig – genau wie Mama!\\nLass sie uns zusammen besiegen, Oma!"
            },
            {
              "type": "Int",
              "value": "0"
            }
          ],
          "children": []
        },
        {
          "name": "TEXT_INFO_8",
          "variables": [
            {
              "type": "Int",
              "value": "2059193861"
            },
            {
              "type": "Int",
              "value": "0"
            },
            {
              "type": "String",
              "value": "Na klar, Schätzchen. Auf zur Gorgonenjagd!"
            },
            {
              "type": "Int",
              "value": "0"
            }
          ],
          "children": []
        },
        {
          "name": "TEXT_INFO_9",
          "variables": [
            {
              "type": "Int",
              "value": "-1430511749"
            },
            {
              "type": "Int",
              "value": "0"
            },
            {
              "type": "String",
              "value": "Danke nochmal, mein Lieber."
            },
            {
              "type": "Int",
              "value": "0"
            }
          ],
          "children": []
        },
        {
          "name": "TEXT_INFO_10",
          "variables": [
            {
              "type": "Int",
              "value": "-1280889286"
            },
            {
              "type": "Int",
              "value": "0"
            },
            {
              "type": "String",
              "value": "Tschüss, Mister!"
            },
            {
              "type": "Int",
              "value": "0"
            }
          ],
          "children": []
        }
      ]
    }
  ]
}