{
  "entries": [
    {
      "name": "TEXT_INFO_BEGIN_0",
      "variables": [
        {
          "type": "Int",
          "value": "11"
        }
      ],
      "children": [
        {
          "name": "TEXT_INFO_0",
          "variables": [
            {
              "type": "Int",
              "value": "1182659526"
            },
            {
              "type": "Int",
              "value": "0"
            },
            {
              "type": "String",
              "value": "Perché giocate così?!\\nVi sta bene perdere?!"
            },
            {
              "type": "Int",
              "value": "0"
            }
          ],
          "children": []
        },
        {
          "name": "TEXT_INFO_1",
          "variables": [
            {
              "type": "Int",
              "value": "1834000389"
            },
            {
              "type": "Int",
              "value": "0"
            },
            {
              "type": "String",
              "value": "Uff..."
            },
            {
              "type": "Int",
              "value": "0"
            }
          ],
          "children": []
        },
        {
          "name": "TEXT_INFO_2",
          "variables": [
            {
              "type": "Int",
              "value": "490361994"
            },
            {
              "type": "Int",
              "value": "0"
            },
            {
              "type": "String",
              "value": "Non m'importa se perdiamo."
            },
            {
              "type": "Int",
              "value": "0"
            }
          ],
          "children": []
        },
        {
          "name": "TEXT_INFO_3",
          "variables": [
            {
              "type": "Int",
              "value": "1951109444"
            },
            {
              "type": "Int",
              "value": "0"
            },
            {
              "type": "String",
              "value": "Era stato deciso fin dall'inizio che la Raimon avrebbe perso 3-0."
            },
            {
              "type": "Int",
              "value": "0"
            }
          ],
          "children": []
        },
        {
          "name": "TEXT_INFO_4",
          "variables": [
            {
              "type": "Int",
              "value": "990513027"
            },
            {
              "type": "Int",
              "value": "0"
            },
            {
              "type": "String",
              "value": "Già deciso?\\nMa che sta dicendo?!"
            },
            {
              "type": "Int",
              "value": "0"
            }
          ],
          "children": []
        },
        {
          "name": "TEXT_INFO_5",
          "variables": [
            {
              "type": "Int",
              "value": "571553474"
            },
            {
              "type": "Int",
              "value": "0"
            },
            {
              "type": "String",
              "value": "Il Quinto Settore controlla esiti e punteggi di ogni partita,\\npoi li comunica alle scuole... il tutto per mantenere \"l'ordine\"."
            },
            {
              "type": "Int",
              "value": "0"
            }
          ],
          "children": []
        },
        {
          "name": "TEXT_INFO_6",
          "variables": [
            {
              "type": "Int",
              "value": "154952961"
            },
            {
              "type": "Int",
              "value": "0"
            },
            {
              "type": "String",
              "value": "Assurdo!\\nDecidere il risultato prima della partita?\\nNon è calcio!"
            },
            {
              "type": "Int",
              "value": "0"
            }
          ],
          "children": []
        },
        {
          "name": "TEXT_INFO_7",
          "variables": [
            {
              "type": "Int",
              "value": "271012928"
            },
            {
              "type": "Int",
              "value": "0"
            },
            {
              "type": "String",
              "value": "Tu che ne sai!\\nNon sai cosa significhi giocare così..."
            },
            {
              "type": "Int",
              "value": "0"
            }
          ],
          "children": []
        },
        {
          "name": "TEXT_INFO_8",
          "variables": [
            {
              "type": "Int",
              "value": "-1749071729"
            },
            {
              "type": "Int",
              "value": "0"
            },
            {
              "type": "String",
              "value": "Anche noi vorremmo giocare sul serio.\\nMa guai a disobbedire al Quinto Settore...\\nPerderemmo il diritto di scendere in campo."
            },
            {
              "type": "Int",
              "value": "0"
            }
          ],
          "children": []
        },
        {
          "name": "TEXT_INFO_9",
          "variables": [
            {
              "type": "Int",
              "value": "-1901823538"
            },
            {
              "type": "Int",
              "value": "0"
            },
            {
              "type": "String",
              "value": "È per questo che noi...!"
            },
            {
              "type": "Int",
              "value": "0"
            }
          ],
          "children": []
        },
        {
          "name": "TEXT_INFO_10",
          "variables": [
            {
              "type": "Int",
              "value": "1587849392"
            },
            {
              "type": "Int",
              "value": "0"
            },
            {
              "type": "String",
              "value": "..."
            },
            {
              "type": "Int",
              "value": "0"
            }
          ],
          "children": []
        }
      ]
    }
  ]
}