{
  "entries": [
    {
      "name": "TEXT_INFO_BEGIN_0",
      "variables": [
        {
          "type": "Int",
          "value": "1"
        }
      ],
      "children": [
        {
          "name": "TEXT_INFO_0",
          "variables": [
            {
              "type": "Int",
              "value": "1235651794"
            },
            {
              "type": "Int",
              "value": "0"
            },
            {
              "type": "String",
              "value": "ちっと\u3000[体力/たいりょく]やべぇな…。"
            },
            {
              "type": "Int",
              "value": "0"
            }
          ],
          "children": []
        }
      ]
    }
  ]
}