{
  "entries": [
    {
      "name": "TEXT_INFO_BEGIN_0",
      "variables": [
        {
          "type": "Int",
          "value": "4"
        }
      ],
      "children": [
        {
          "name": "TEXT_INFO_0",
          "variables": [
            {
              "type": "Int",
              "value": "840619159"
            },
            {
              "type": "Int",
              "value": "0"
            },
            {
              "type": "String",
              "value": "Bon sang ! Il faut que j'arrête le prochain !"
            },
            {
              "type": "Int",
              "value": "0"
            }
          ],
          "children": []
        },
        {
          "name": "TEXT_INFO_1",
          "variables": [
            {
              "type": "Int",
              "value": "423069524"
            },
            {
              "type": "Int",
              "value": "0"
            },
            {
              "type": "String",
              "value": "Hé, but."
            },
            {
              "type": "Int",
              "value": "0"
            }
          ],
          "children": []
        },
        {
          "name": "TEXT_INFO_2",
          "variables": [
            {
              "type": "Int",
              "value": "2930197"
            },
            {
              "type": "Int",
              "value": "0"
            },
            {
              "type": "String",
              "value": "<FUL:MINAMISAWA2>, ce tir était incroyable..."
            },
            {
              "type": "Int",
              "value": "0"
            }
          ],
          "children": []
        },
        {
          "name": "TEXT_INFO_3",
          "variables": [
            {
              "type": "Int",
              "value": "1332551890"
            },
            {
              "type": "Int",
              "value": "0"
            },
            {
              "type": "String",
              "value": "Aller, je vais tout donner moi aussi !"
            },
            {
              "type": "Int",
              "value": "0"
            }
          ],
          "children": []
        }
      ]
    }
  ]
}